{
  "info": {
    "name": "GoPortal API",
    "_postman_id": "7a0b6f2f-b3f9-4bd9-8ad9-9f6c52789af0",
    "description": "Auth, profile, social, server, RBAC role, invite, channel, messaging, upload, and reaction APIs.",
    "schema": "https://schema.getpostman.com/json/collection/v2.1.0/collection.json"
  },
  "item": [
    {
      "name": "Auth",
      "item": [
        {
          "name": "Register",
          "request": {
            "method": "POST",
            "header": [
              {
                "key": "Content-Type",
                "value": "application/json"
              }
            ],
            "url": {
              "raw": "{{base_url}}/api/v1/auth/register",
              "host": [
                "{{base_url}}"
              ],
              "path": [
                "api",
                "v1",
                "auth",
                "register"
              ]
            },
            "body": {
              "mode": "raw",
              "raw": "{\n  \"username\": \"john\",\n  \"password\": \"password123\"\n}"
            },
            "description": "Create a new user account.\n\nSuccess: 201 User created\nConflict: 409 USERNAME_EXISTS"
          }
        },
        {
          "name": "Login",
          "request": {
            "method": "POST",
            "header": [
              {
                "key": "Content-Type",
                "value": "application/json"
              }
            ],
            "url": {
              "raw": "{{base_url}}/api/v1/auth/login",
              "host": [
                "{{base_url}}"
              ],
              "path": [
                "api",
                "v1",
                "auth",
                "login"
              ]
            },
            "body": {
              "mode": "raw",
              "raw": "{\n  \"username\": \"john\",\n  \"password\": \"password123\"\n}"
            },
            "description": "Authenticate and receive JWT token.\n\nSuccess: 200 includes data.token\nUnauthorized: 401 BAD_CREDENTIALS"
          }
        }
      ]
    },
    {
      "name": "Users",
      "item": [
        {
          "name": "Get Current User",
          "request": {
            "method": "GET",
            "header": [
              {
                "key": "Authorization",
                "value": "Bearer {{token}}"
              }
            ],
            "url": {
              "raw": "{{base_url}}/api/v1/users/me",
              "host": [
                "{{base_url}}"
              ],
              "path": [
                "api",
                "v1",
                "users",
                "me"
              ]
            },
            "description": "Get current authenticated user profile."
          }
        },
        {
          "name": "Update Current User",
          "request": {
            "method": "PATCH",
            "header": [
              {
                "key": "Authorization",
                "value": "Bearer {{token}}"
              },
              {
                "key": "Content-Type",
                "value": "application/json"
              }
            ],
            "url": {
              "raw": "{{base_url}}/api/v1/users/me",
              "host": [
                "{{base_url}}"
              ],
              "path": [
                "api",
                "v1",
                "users",
                "me"
              ]
            },
            "body": {
              "mode": "raw",
              "raw": "{\n  \"username\": \"john-updated\"\n}"
            },
            "description": "Update current user profile.\n\nSuccess: 200\nConflict: 409 USERNAME_EXISTS"
          }
        }
      ]
    },
    {
      "name": "Friends",
      "item": [
        {
          "name": "List Friends",
          "request": {
            "method": "GET",
            "header": [
              {
                "key": "Authorization",
                "value": "Bearer {{token}}"
              }
            ],
            "url": {
              "raw": "{{base_url}}/api/v1/friends",
              "host": [
                "{{base_url}}"
              ],
              "path": [
                "api",
                "v1",
                "friends"
              ]
            },
            "description": "List accepted friends for current user."
          }
        },
        {
          "name": "Send Friend Request",
          "request": {
            "method": "POST",
            "header": [
              {
                "key": "Authorization",
                "value": "Bearer {{token}}"
              },
              {
                "key": "Content-Type",
                "value": "application/json"
              }
            ],
            "url": {
              "raw": "{{base_url}}/api/v1/friends/request",
              "host": [
                "{{base_url}}"
              ],
              "path": [
                "api",
                "v1",
                "friends",
                "request"
              ]
            },
            "body": {
              "mode": "raw",
              "raw": "{\n  \"user_id\": \"target-user-uuid\"\n}"
            },
            "description": "Send a friend request.\n\nValidation: cannot send to self\nConflict: FRIEND_REQUEST_EXISTS or ALREADY_FRIENDS"
          }
        },
        {
          "name": "Respond Friend Request",
          "request": {
            "method": "PATCH",
            "header": [
              {
                "key": "Authorization",
                "value": "Bearer {{token}}"
              },
              {
                "key": "Content-Type",
                "value": "application/json"
              }
            ],
            "url": {
              "raw": "{{base_url}}/api/v1/friends/response",
              "host": [
                "{{base_url}}"
              ],
              "path": [
                "api",
                "v1",
                "friends",
                "response"
              ]
            },
            "body": {
              "mode": "raw",
              "raw": "{\n  \"requester_id\": \"requester-user-uuid\",\n  \"action\": \"ACCEPT\"\n}"
            },
            "description": "Respond to incoming friend request.\nAction can be ACCEPT or DECLINE."
          }
        },
        {
          "name": "Block User",
          "request": {
            "method": "PATCH",
            "header": [
              {
                "key": "Authorization",
                "value": "Bearer {{token}}"
              },
              {
                "key": "Content-Type",
                "value": "application/json"
              }
            ],
            "url": {
              "raw": "{{base_url}}/api/v1/friends/block",
              "host": [
                "{{base_url}}"
              ],
              "path": [
                "api",
                "v1",
                "friends",
                "block"
              ]
            },
            "body": {
              "mode": "raw",
              "raw": "{\n  \"user_id\": \"target-user-uuid\"\n}"
            },
            "description": "Block a user.\n\nValidation: cannot block self"
          }
        }
      ]
    },
    {
      "name": "Servers",
      "item": [
        {
          "name": "Create Server",
          "request": {
            "method": "POST",
            "header": [
              {
                "key": "Authorization",
                "value": "Bearer {{token}}"
              },
              {
                "key": "Content-Type",
                "value": "application/json"
              }
            ],
            "url": {
              "raw": "{{base_url}}/api/v1/servers",
              "host": [
                "{{base_url}}"
              ],
              "path": [
                "api",
                "v1",
                "servers"
              ]
            },
            "body": {
              "mode": "raw",
              "raw": "{\n  \"name\": \"Backend Team\",\n  \"is_public\": true\n}"
            },
            "description": "Create a server (guild).\n\nBusiness rule: creator becomes owner and first member."
          }
        },
        {
          "name": "Join Public Server",
          "request": {
            "method": "POST",
            "header": [
              {
                "key": "Authorization",
                "value": "Bearer {{token}}"
              }
            ],
            "url": {
              "raw": "{{base_url}}/api/v1/servers/{{server_id}}/join",
              "host": [
                "{{base_url}}"
              ],
              "path": [
                "api",
                "v1",
                "servers",
                "{{server_id}}",
                "join"
              ]
            },
            "description": "Join a public server. Backend auto-assigns default_role_id."
          }
        },
        {
          "name": "List Server Members",
          "request": {
            "method": "GET",
            "header": [
              {
                "key": "Authorization",
                "value": "Bearer {{token}}"
              }
            ],
            "url": {
              "raw": "{{base_url}}/api/v1/servers/{{server_id}}/members",
              "host": [
                "{{base_url}}"
              ],
              "path": [
                "api",
                "v1",
                "servers",
                "{{server_id}}",
                "members"
              ]
            },
            "description": "List members in a server.\n\nCaller must already be a member."
          }
        },
        {
          "name": "Update Member Roles",
          "request": {
            "method": "PATCH",
            "header": [
              {
                "key": "Authorization",
                "value": "Bearer {{token}}"
              },
              {
                "key": "Content-Type",
                "value": "application/json"
              }
            ],
            "url": {
              "raw": "{{base_url}}/api/v1/servers/{{server_id}}/members/{{member_user_id}}/roles",
              "host": [
                "{{base_url}}"
              ],
              "path": [
                "api",
                "v1",
                "servers",
                "{{server_id}}",
                "members",
                "{{member_user_id}}",
                "roles"
              ]
            },
            "body": {
              "mode": "raw",
              "raw": "{\n  \"role_ids\": [\n    \"{{role_id}}\"\n  ]\n}"
            },
            "description": "Replace roles for a server member. Requires MANAGE_SERVER/ADMINISTRATOR."
          }
        },
        {
          "name": "Create Role",
          "request": {
            "method": "POST",
            "header": [
              {
                "key": "Authorization",
                "value": "Bearer {{token}}"
              },
              {
                "key": "Content-Type",
                "value": "application/json"
              }
            ],
            "url": {
              "raw": "{{base_url}}/api/v1/servers/{{server_id}}/roles",
              "host": [
                "{{base_url}}"
              ],
              "path": [
                "api",
                "v1",
                "servers",
                "{{server_id}}",
                "roles"
              ]
            },
            "body": {
              "mode": "raw",
              "raw": "{\n  \"name\": \"moderator\",\n  \"permissions\": [1, 2, 4]\n}"
            },
            "description": "Create role in a server."
          }
        },
        {
          "name": "Create Invite Link",
          "request": {
            "method": "POST",
            "header": [
              {
                "key": "Authorization",
                "value": "Bearer {{token}}"
              },
              {
                "key": "Content-Type",
                "value": "application/json"
              }
            ],
            "url": {
              "raw": "{{base_url}}/api/v1/servers/{{server_id}}/invites",
              "host": [
                "{{base_url}}"
              ],
              "path": [
                "api",
                "v1",
                "servers",
                "{{server_id}}",
                "invites"
              ]
            },
            "body": {
              "mode": "raw",
              "raw": "{\n  \"max_uses\": 10,\n  \"expires_at\": 1770000000\n}"
            },
            "description": "Create invite code. Requires CREATE_INVITE/ADMINISTRATOR."
          }
        },
        {
          "name": "Delete Server (Owner Only)",
          "request": {
            "method": "DELETE",
            "header": [
              {
                "key": "Authorization",
                "value": "Bearer {{token}}"
              }
            ],
            "url": {
              "raw": "{{base_url}}/api/v1/servers/{{server_id}}",
              "host": [
                "{{base_url}}"
              ],
              "path": [
                "api",
                "v1",
                "servers",
                "{{server_id}}"
              ]
            },
            "description": "Delete a server.\n\nOnly owner can delete."
          }
        },
        {
          "name": "Kick Member (Owner Only)",
          "request": {
            "method": "DELETE",
            "header": [
              {
                "key": "Authorization",
                "value": "Bearer {{token}}"
              }
            ],
            "url": {
              "raw": "{{base_url}}/api/v1/servers/{{server_id}}/members/{{member_user_id}}",
              "host": [
                "{{base_url}}"
              ],
              "path": [
                "api",
                "v1",
                "servers",
                "{{server_id}}",
                "members",
                "{{member_user_id}}"
              ]
            },
            "description": "Kick a member from server.\n\nOnly owner can kick and owner cannot be kicked."
          }
        },
        {
          "name": "Create Channel In Server",
          "request": {
            "method": "POST",
            "header": [
              {
                "key": "Authorization",
                "value": "Bearer {{token}}"
              },
              {
                "key": "Content-Type",
                "value": "application/json"
              }
            ],
            "url": {
              "raw": "{{base_url}}/api/v1/servers/{{server_id}}/channels",
              "host": [
                "{{base_url}}"
              ],
              "path": [
                "api",
                "v1",
                "servers",
                "{{server_id}}",
                "channels"
              ]
            },
            "body": {
              "mode": "raw",
              "raw": "{\n  \"name\": \"general\",\n  \"type\": \"TEXT\",\n  \"parent_id\": \"{{category_channel_id}}\",\n  \"position\": 0\n}"
            },
            "description": "Create channel in a server.\n\nSupported types: TEXT, VOICE, CATEGORY."
          }
        },
        {
          "name": "Create Join Request",
          "request": {
            "method": "POST",
            "header": [
              {
                "key": "Authorization",
                "value": "Bearer {{token}}"
              },
              {
                "key": "Content-Type",
                "value": "application/json"
              }
            ],
            "url": {
              "raw": "{{base_url}}/api/v1/servers/{{server_id}}/join-requests",
              "host": [
                "{{base_url}}"
              ],
              "path": [
                "api",
                "v1",
                "servers",
                "{{server_id}}",
                "join-requests"
              ]
            },
            "description": "Create pending join request.",
            "body": {
              "mode": "raw",
              "raw": "{\n  \"note\": \"Please allow me to join\"\n}"
            }
          }
        },
        {
          "name": "List Join Requests",
          "request": {
            "method": "GET",
            "header": [
              {
                "key": "Authorization",
                "value": "Bearer {{token}}"
              }
            ],
            "url": {
              "raw": "{{base_url}}/api/v1/servers/{{server_id}}/join-requests?status=pending",
              "host": [
                "{{base_url}}"
              ],
              "path": [
                "api",
                "v1",
                "servers",
                "{{server_id}}",
                "join-requests?status=pending"
              ]
            },
            "description": "List join requests by status."
          }
        },
        {
          "name": "Review Join Request",
          "request": {
            "method": "PATCH",
            "header": [
              {
                "key": "Authorization",
                "value": "Bearer {{token}}"
              },
              {
                "key": "Content-Type",
                "value": "application/json"
              }
            ],
            "url": {
              "raw": "{{base_url}}/api/v1/servers/{{server_id}}/join-requests/{{request_id}}",
              "host": [
                "{{base_url}}"
              ],
              "path": [
                "api",
                "v1",
                "servers",
                "{{server_id}}",
                "join-requests",
                "{{request_id}}"
              ]
            },
            "description": "Approve or reject join request.",
            "body": {
              "mode": "raw",
              "raw": "{\n  \"approve\": true,\n  \"note\": \"Welcome\"\n}"
            }
          }
        },
        {
          "name": "Add Member",
          "request": {
            "method": "POST",
            "header": [
              {
                "key": "Authorization",
                "value": "Bearer {{token}}"
              },
              {
                "key": "Content-Type",
                "value": "application/json"
              }
            ],
            "url": {
              "raw": "{{base_url}}/api/v1/servers/{{server_id}}/members",
              "host": [
                "{{base_url}}"
              ],
              "path": [
                "api",
                "v1",
                "servers",
                "{{server_id}}",
                "members"
              ]
            },
            "description": "Add existing user into server with default role.",
            "body": {
              "mode": "raw",
              "raw": "{\n  \"user_id\": \"{{target_user_id}}\"\n}"
            }
          }
        },
        {
          "name": "List My Servers",
          "request": {
            "method": "GET",
            "header": [
              {
                "key": "Authorization",
                "value": "Bearer {{token}}"
              }
            ],
            "url": {
              "raw": "{{base_url}}/api/v1/servers",
              "host": [
                "{{base_url}}"
              ],
              "path": [
                "api",
                "v1",
                "servers"
              ]
            },
            "description": "List active servers current user joined/owns."
          }
        },
        {
          "name": "List Server Channels",
          "request": {
            "method": "GET",
            "header": [
              {
                "key": "Authorization",
                "value": "Bearer {{token}}"
              }
            ],
            "url": {
              "raw": "{{base_url}}/api/v1/servers/{{server_id}}/channels",
              "host": [
                "{{base_url}}"
              ],
              "path": [
                "api",
                "v1",
                "servers",
                "{{server_id}}",
                "channels"
              ]
            },
            "description": "List channels visible to current user in the server."
          }
        }
      ]
    },
    {
      "name": "Roles",
      "item": [
        {
          "name": "Update Role",
          "request": {
            "method": "PATCH",
            "header": [
              {
                "key": "Authorization",
                "value": "Bearer {{token}}"
              },
              {
                "key": "Content-Type",
                "value": "application/json"
              }
            ],
            "url": {
              "raw": "{{base_url}}/api/v1/roles/{{role_id}}",
              "host": [
                "{{base_url}}"
              ],
              "path": [
                "api",
                "v1",
                "roles",
                "{{role_id}}"
              ]
            },
            "body": {
              "mode": "raw",
              "raw": "{\n  \"name\": \"moderator\",\n  \"permissions\": [\n    1,\n    2,\n    4\n  ],\n  \"position\": 50\n}"
            },
            "description": "Update role metadata and bit permissions."
          }
        }
      ]
    },
    {
      "name": "Invites",
      "item": [
        {
          "name": "Get Invite Info",
          "request": {
            "method": "GET",
            "header": [],
            "url": {
              "raw": "{{base_url}}/api/v1/invites/{{invite_code}}",
              "host": [
                "{{base_url}}"
              ],
              "path": [
                "api",
                "v1",
                "invites",
                "{{invite_code}}"
              ]
            },
            "description": "Get invite metadata and target server summary."
          }
        },
        {
          "name": "Join By Invite",
          "request": {
            "method": "POST",
            "header": [
              {
                "key": "Authorization",
                "value": "Bearer {{token}}"
              }
            ],
            "url": {
              "raw": "{{base_url}}/api/v1/invites/{{invite_code}}/join",
              "host": [
                "{{base_url}}"
              ],
              "path": [
                "api",
                "v1",
                "invites",
                "{{invite_code}}",
                "join"
              ]
            },
            "description": "Join a server via invite code."
          }
        }
      ]
    },
    {
      "name": "Channels",
      "item": [
        {
          "name": "Get Channel By ID",
          "request": {
            "method": "GET",
            "header": [
              {
                "key": "Authorization",
                "value": "Bearer {{token}}"
              }
            ],
            "url": {
              "raw": "{{base_url}}/api/v1/channels/{{channel_id}}",
              "host": [
                "{{base_url}}"
              ],
              "path": [
                "api",
                "v1",
                "channels",
                "{{channel_id}}"
              ]
            },
            "description": "Get channel detail by ID.\n\nCaller must be a member of the channel's server."
          }
        },
        {
          "name": "Update Channel Position",
          "request": {
            "method": "PATCH",
            "header": [
              {
                "key": "Authorization",
                "value": "Bearer {{token}}"
              },
              {
                "key": "Content-Type",
                "value": "application/json"
              }
            ],
            "url": {
              "raw": "{{base_url}}/api/v1/channels/{{channel_id}}/position",
              "host": [
                "{{base_url}}"
              ],
              "path": [
                "api",
                "v1",
                "channels",
                "{{channel_id}}",
                "position"
              ]
            },
            "body": {
              "mode": "raw",
              "raw": "{\n  \"position\": 2\n}"
            },
            "description": "Update a channel's integer position for sorting."
          }
        },
        {
          "name": "Update Privacy",
          "request": {
            "method": "PATCH",
            "header": [
              {
                "key": "Authorization",
                "value": "Bearer {{token}}"
              },
              {
                "key": "Content-Type",
                "value": "application/json"
              }
            ],
            "url": {
              "raw": "{{base_url}}/api/v1/channels/{{channel_id}}/privacy",
              "host": [
                "{{base_url}}"
              ],
              "path": [
                "api",
                "v1",
                "channels",
                "{{channel_id}}",
                "privacy"
              ]
            },
            "description": "Toggle private channel mode.",
            "body": {
              "mode": "raw",
              "raw": "{\n  \"is_private\": true\n}"
            }
          }
        },
        {
          "name": "List Members",
          "request": {
            "method": "GET",
            "header": [
              {
                "key": "Authorization",
                "value": "Bearer {{token}}"
              }
            ],
            "url": {
              "raw": "{{base_url}}/api/v1/channels/{{channel_id}}/members",
              "host": [
                "{{base_url}}"
              ],
              "path": [
                "api",
                "v1",
                "channels",
                "{{channel_id}}",
                "members"
              ]
            },
            "description": "List channel members."
          }
        },
        {
          "name": "Add Member",
          "request": {
            "method": "POST",
            "header": [
              {
                "key": "Authorization",
                "value": "Bearer {{token}}"
              },
              {
                "key": "Content-Type",
                "value": "application/json"
              }
            ],
            "url": {
              "raw": "{{base_url}}/api/v1/channels/{{channel_id}}/members",
              "host": [
                "{{base_url}}"
              ],
              "path": [
                "api",
                "v1",
                "channels",
                "{{channel_id}}",
                "members"
              ]
            },
            "description": "Add member to channel.",
            "body": {
              "mode": "raw",
              "raw": "{\n  \"user_id\": \"{{target_user_id}}\"\n}"
            }
          }
        },
        {
          "name": "Remove Member",
          "request": {
            "method": "DELETE",
            "header": [
              {
                "key": "Authorization",
                "value": "Bearer {{token}}"
              }
            ],
            "url": {
              "raw": "{{base_url}}/api/v1/channels/{{channel_id}}/members/{{target_user_id}}",
              "host": [
                "{{base_url}}"
              ],
              "path": [
                "api",
                "v1",
                "channels",
                "{{channel_id}}",
                "members",
                "{{target_user_id}}"
              ]
            },
            "description": "Remove member from channel."
          }
        },
        {
          "name": "List Overwrites",
          "request": {
            "method": "GET",
            "header": [
              {
                "key": "Authorization",
                "value": "Bearer {{token}}"
              }
            ],
            "url": {
              "raw": "{{base_url}}/api/v1/channels/{{channel_id}}/overwrites",
              "host": [
                "{{base_url}}"
              ],
              "path": [
                "api",
                "v1",
                "channels",
                "{{channel_id}}",
                "overwrites"
              ]
            },
            "description": "List channel permission overwrites."
          }
        },
        {
          "name": "Upsert Overwrite",
          "request": {
            "method": "PUT",
            "header": [
              {
                "key": "Authorization",
                "value": "Bearer {{token}}"
              },
              {
                "key": "Content-Type",
                "value": "application/json"
              }
            ],
            "url": {
              "raw": "{{base_url}}/api/v1/channels/{{channel_id}}/overwrites",
              "host": [
                "{{base_url}}"
              ],
              "path": [
                "api",
                "v1",
                "channels",
                "{{channel_id}}",
                "overwrites"
              ]
            },
            "description": "Upsert channel overwrite.",
            "body": {
              "mode": "raw",
              "raw": "{\n  \"subject_type\": \"ROLE\",\n  \"subject_id\": \"{{role_id}}\",\n  \"allow_bits\": 1,\n  \"deny_bits\": 2\n}"
            }
          }
        },
        {
          "name": "Delete Overwrite",
          "request": {
            "method": "DELETE",
            "header": [
              {
                "key": "Authorization",
                "value": "Bearer {{token}}"
              }
            ],
            "url": {
              "raw": "{{base_url}}/api/v1/channels/{{channel_id}}/overwrites/ROLE/{{role_id}}",
              "host": [
                "{{base_url}}"
              ],
              "path": [
                "api",
                "v1",
                "channels",
                "{{channel_id}}",
                "overwrites",
                "ROLE",
                "{{role_id}}"
              ]
            },
            "description": "Delete channel overwrite."
          }
        }
      ]
    },
    {
      "name": "Uploads",
      "item": [
        {
          "name": "Upload Attachment",
          "request": {
            "method": "POST",
            "header": [
              {
                "key": "Authorization",
                "value": "Bearer {{token}}"
              }
            ],
            "url": {
              "raw": "{{base_url}}/api/v1/upload",
              "host": [
                "{{base_url}}"
              ],
              "path": [
                "api",
                "v1",
                "upload"
              ]
            },
            "body": {
              "mode": "formdata",
              "formdata": [
                {
                  "key": "file",
                  "type": "file",
                  "src": ""
                }
              ]
            },
            "description": "Upload file attachment. Allowed: image/*, pdf, zip. Max: 10MB."
          }
        }
      ]
    },
    {
      "name": "Messages",
      "item": [
        {
          "name": "List Channel Messages",
          "request": {
            "method": "GET",
            "header": [
              {
                "key": "Authorization",
                "value": "Bearer {{token}}"
              }
            ],
            "url": {
              "raw": "{{base_url}}/api/v1/channels/{{channel_id}}/messages?limit=20&offset=0",
              "host": [
                "{{base_url}}"
              ],
              "path": [
                "api",
                "v1",
                "channels",
                "{{channel_id}}",
                "messages"
              ],
              "query": [
                {
                  "key": "limit",
                  "value": "20"
                },
                {
                  "key": "offset",
                  "value": "0"
                }
              ]
            },
            "description": "Fetch channel messages with pagination."
          }
        },
        {
          "name": "Create Message",
          "request": {
            "method": "POST",
            "header": [
              {
                "key": "Authorization",
                "value": "Bearer {{token}}"
              },
              {
                "key": "Content-Type",
                "value": "application/json"
              }
            ],
            "url": {
              "raw": "{{base_url}}/api/v1/messages",
              "host": [
                "{{base_url}}"
              ],
              "path": [
                "api",
                "v1",
                "messages"
              ]
            },
            "body": {
              "mode": "raw",
              "raw": "{\n  \"channel_id\": \"{{channel_id}}\",\n  \"content_type\": \"text/plain\",\n  \"content\": \"Hello from Postman\",\n  \"encoding\": \"utf-8\",\n  \"is_pinned\": false,\n  \"attachment_ids\": [\n    \"{{attachment_id}}\"\n  ]\n}"
            },
            "description": "Create message and publish Watermill event to chat.message.created."
          }
        },
        {
          "name": "Edit Message",
          "request": {
            "method": "PATCH",
            "header": [
              {
                "key": "Authorization",
                "value": "Bearer {{token}}"
              },
              {
                "key": "Content-Type",
                "value": "application/json"
              }
            ],
            "url": {
              "raw": "{{base_url}}/api/v1/messages/{{message_id}}",
              "host": [
                "{{base_url}}"
              ],
              "path": [
                "api",
                "v1",
                "messages",
                "{{message_id}}"
              ]
            },
            "body": {
              "mode": "raw",
              "raw": "{\n  \"content_type\": \"text/plain\",\n  \"content\": \"edited text\",\n  \"encoding\": \"utf-8\"\n}"
            },
            "description": "Edit message content (author only)."
          }
        },
        {
          "name": "Delete Message",
          "request": {
            "method": "DELETE",
            "header": [
              {
                "key": "Authorization",
                "value": "Bearer {{token}}"
              }
            ],
            "url": {
              "raw": "{{base_url}}/api/v1/messages/{{message_id}}",
              "host": [
                "{{base_url}}"
              ],
              "path": [
                "api",
                "v1",
                "messages",
                "{{message_id}}"
              ]
            },
            "description": "Soft-delete a message (author only)."
          }
        },
        {
          "name": "Toggle Reaction",
          "request": {
            "method": "POST",
            "header": [
              {
                "key": "Authorization",
                "value": "Bearer {{token}}"
              },
              {
                "key": "Content-Type",
                "value": "application/json"
              }
            ],
            "url": {
              "raw": "{{base_url}}/api/v1/messages/{{message_id}}/reactions",
              "host": [
                "{{base_url}}"
              ],
              "path": [
                "api",
                "v1",
                "messages",
                "{{message_id}}",
                "reactions"
              ]
            },
            "body": {
              "mode": "raw",
              "raw": "{\n  \"emoji\": \"\ud83d\udd25\"\n}"
            },
            "description": "Toggle reaction for current user on target message."
          }
        }
      ]
    }
  ]
}
